[{"firstName":"Cúc","surName":"Tấn Tông","birthday":"2001-09-02","gender":"Nam","national":"Việt Nam","ethnic":"Kinh","religion":"Không có","bornAddress":"100 Liêu Tri, Cai Vương, Ánh Sùng","homeAddress":"313 Lại Tông, Dương Trà, Ung An","citizenCardId":"9136362689","currentAddress":"5 Trương Tinh, Đống Chung, Trương Đức","phoneNumber":"3852096289","email":"vhalwood0@technorati.com","fatherPhoneNumber":"7037930102","motherPhoneNumber":"8191586155","isEnlisted":false,"draftDate":"","school":"UET","academyMethod":"Chính quy","levelOfAcademy":"Sinh viên","startedYear":"2010","schoolYearGroup":"K10","baseClass":"QH-2010","major":"Hệ thống thông tin"},
{"firstName":"Khâu","surName":"Ánh Hình","birthday":"1997-10-04","gender":"Nam","national":"Nga","ethnic":"Mông","religion":"Tin Lành","bornAddress":"365 Tạ Yên, Bành Dương, Bạch Khuất","homeAddress":"215 Huỳnh Luyện, Lại Ung, H’ Quách","citizenCardId":"4553593599","currentAddress":"25 Phùng Lại, Khoa Cai, Xa Dương","phoneNumber":"2256603445","email":"jtrapp1@google.es","fatherPhoneNumber":"2432162112","motherPhoneNumber":"9944255458","isEnlisted":false,"draftDate":"","school":"UET","academyMethod":"Chính quy","levelOfAcademy":"Sinh viên","startedYear":"2018","schoolYearGroup":"K18","baseClass":"QH-2018","major":"Mạng máy tính và truyền thông dữ liệu"},
{"firstName":"Bính","surName":"Võ Ninh","birthday":"2000-09-14","gender":"Nữ","national":"Việt Nam","ethnic":"Kinh","religion":"Hồi giáo","bornAddress":"403 Giang Ong, Trang Đức, Liên Kông","homeAddress":"121 Hồng Lạc, Đăng Thân, Bành Quách","citizenCardId":"2728374805","currentAddress":"60 Hoa Cung, Liễu Khương, Hề Nông","phoneNumber":"7987239742","email":"sorsay2@freewebs.com","fatherPhoneNumber":"3659975207","motherPhoneNumber":"7147270495","isEnlisted":false,"draftDate":"","school":"UET","academyMethod":"Chính quy","levelOfAcademy":"Sinh viên","startedYear":"2007","schoolYearGroup":"K07","baseClass":"QH-2007","major":"Công nghệ Hàng không vũ trụ"},
{"firstName":"Hà","surName":"Lãnh Ân","birthday":"1993-02-22","gender":"Nam","national":"Việt Nam","ethnic":"Kinh","religion":"Không có","bornAddress":"107 Tôn Lò, Bồ Quang, Khâu Võ","homeAddress":"181 Lục Chương, Cồ Thịnh, Bế Lạc","citizenCardId":"6187431383","currentAddress":"137 Lại Tiếp, Giả Kiều, Khổng Sơn","phoneNumber":"1005388960","email":"chains3@npr.org","fatherPhoneNumber":"7701619617","motherPhoneNumber":"7254838801","isEnlisted":false,"draftDate":"","school":"UET","academyMethod":"Chính quy","levelOfAcademy":"Sinh viên","startedYear":"2011","schoolYearGroup":"K11","baseClass":"QH-2011","major":"Công nghệ kỹ thuật xây dựng"},
{"firstName":"Nhĩ","surName":"Ánh Tấn","birthday":"2005-03-02","gender":"Nam","national":"Việt Nam","ethnic":"Mường","religion":"Không có","bornAddress":"161 Thịnh Chương, Chiêm Tán, Điền Ung","homeAddress":"492 Tinh Bế, Thất Đinh, Cự Mộc","citizenCardId":"6872359277","currentAddress":"411 Ninh Liêu, Mạch Xung, Hàn Bành","phoneNumber":"2458600908","email":"ccoaten4@cbsnews.com","fatherPhoneNumber":"5012608804","motherPhoneNumber":"9844625878","isEnlisted":false,"draftDate":"","school":"UET","academyMethod":"Chính quy","levelOfAcademy":"Sinh viên","startedYear":"2013","schoolYearGroup":"K13","baseClass":"CA-CLC-2013","major":"Công nghệ kỹ thuật xây dựng"},
{"firstName":"Bách","surName":"Ngọc La","birthday":"1994-05-21","gender":"Nam","national":"Việt Nam","ethnic":"Kinh","religion":"Không có","bornAddress":"172 Lều Mã, Đường Lục, Yên Hàn","homeAddress":"464 Hán Mâu, Liêu Đan, Cam Phan","citizenCardId":"4737263109","currentAddress":"116 Nghị Lâm, Dương Hề, Giàng Yên","phoneNumber":"2828745946","email":"sbensen5@163.com","fatherPhoneNumber":"1249115967","motherPhoneNumber":"4612802319","isEnlisted":true,"draftDate":"2018-05-30","school":"UET","academyMethod":"Chính quy","levelOfAcademy":"Sinh viên","startedYear":"2020","schoolYearGroup":"K20","baseClass":"CA-CLC-2020","major":"Kỹ thuật máy tính"},
{"firstName":"Thứ","surName":"Đoạn Quản","birthday":"2001-05-17","gender":"Nam","national":"Việt Nam","ethnic":"Mông","religion":"Không có","bornAddress":"475 Viêm Đôn, Cao Mùa, Hồng Ưng","homeAddress":"486 Hình Chiêm, Chu/Châu Đống, Nhan La","citizenCardId":"9309394102","currentAddress":"401 Sơn Cồ, Doãn Bình, Kiều Ngân","phoneNumber":"3655802190","email":"ddaeth6@cocolog-nifty.com","fatherPhoneNumber":"1416519521","motherPhoneNumber":"6233530980","isEnlisted":false,"draftDate":"","school":"UET","academyMethod":"Chính quy","levelOfAcademy":"Sinh viên","startedYear":"2014","schoolYearGroup":"K14","baseClass":"QH-2014","major":"Công nghệ nông nghiệp"},
{"firstName":"Vui","surName":"Lyly Duy","birthday":"1999-11-23","gender":"Nữ","national":"Việt Nam","ethnic":"Kinh","religion":"Không có","bornAddress":"456 Giang Lỗ, Liên Tri, Lương Cáp","homeAddress":"416 Hình Chương, Kha Hướng, Ca Thân","citizenCardId":"9562161358","currentAddress":"237 Trà Ngô, Mã Bá, Khương An","phoneNumber":"3633341466","email":"dschops7@imageshack.us","fatherPhoneNumber":"5009817336","motherPhoneNumber":"9041142787","isEnlisted":true,"draftDate":"2019-03-18","school":"UET","academyMethod":"Chính quy","levelOfAcademy":"Sinh viên đã tốt nghiệp","startedYear":"2014","schoolYearGroup":"K14","baseClass":"QH-2014","major":"Công nghệ kỹ thuật cơ điện tử"},
{"firstName":"Lập","surName":"Hàn Nguyễn","birthday":"1990-12-31","gender":"Nam","national":"Việt Nam","ethnic":"Kinh","religion":"Thiên Chúa giáo","bornAddress":"51 Chế Danh, Cam Diệp, Tiếp Đặng","homeAddress":"405 Nghị Thẩm, Lê Đan, Đậu Cống","citizenCardId":"9463960333","currentAddress":"236 Chương Tri, Cáp Khuất, Bạch Ao","phoneNumber":"7811898631","email":"gbisterfeld8@delicious.com","fatherPhoneNumber":"9737098764","motherPhoneNumber":"6996438429","isEnlisted":true,"draftDate":"2019-09-05","school":"UET","academyMethod":"Chính quy","levelOfAcademy":"Thạc sĩ","startedYear":"2010","schoolYearGroup":"K10","baseClass":"QH-2010","major":"Công nghệ thông tin"},
{"firstName":"Ðới","surName":"Âu Cát","birthday":"2001-02-01","gender":"Khác","national":"Việt Nam","ethnic":"Kinh","religion":"Không có","bornAddress":"183 Ong Luyện, Danh Ánh, Lại Lục","homeAddress":"434 Mang Đổng, Chu/Châu Thập, Lê  ","citizenCardId":"2560740257","currentAddress":"304 Phó Lyly, Hồ Trang, Phạm Mâu","phoneNumber":"6031089807","email":"djasper9@skype.com","fatherPhoneNumber":"4629898617","motherPhoneNumber":"5531839108","isEnlisted":false,"draftDate":"","school":"UET","academyMethod":"Chính quy","levelOfAcademy":"Sinh viên đã tốt nghiệp","startedYear":"2010","schoolYearGroup":"K10","baseClass":"QH-2010","major":"Kỹ thuật năng lượng"},
{"firstName":"Thục","surName":"Phó Bạc","birthday":"1992-09-09","gender":"Nữ","national":"Việt Nam","ethnic":"Kinh","religion":"Không có","bornAddress":"384 Cao Ngạc, Mang Nhâm, Sái Ca","homeAddress":"107 Chử Quách, Hình Liễu, Chế Lý","citizenCardId":"6005711245","currentAddress":"401 Xung Phùng, Tinh Hi, Bì Trưng","phoneNumber":"8962555768","email":"kwheala@sun.com","fatherPhoneNumber":"9715351562","motherPhoneNumber":"9969835636","isEnlisted":true,"draftDate":"2020-11-09","school":"UET","academyMethod":"Chính quy","levelOfAcademy":"Sinh viên","startedYear":"2017","schoolYearGroup":"K17","baseClass":"QH-2017","major":"Điện Tử Viễn Thông"},
{"firstName":"Ðồng","surName":"Cái Lãnh","birthday":"1999-03-12","gender":"Nam","national":"Việt Nam","ethnic":"Kinh","religion":"Không có","bornAddress":"466 Trình Phan, Ông Phó, Liêu Bàn","homeAddress":"56 Âu Cầm, Bì Khai, Thất Duy","citizenCardId":"1348339012","currentAddress":"416 Chương Ân, Chương Ninh, Ngũ Duy","phoneNumber":"4257146455","email":"fgetcliffb@ucoz.com","fatherPhoneNumber":"1899966993","motherPhoneNumber":"1694631085","isEnlisted":false,"draftDate":"","school":"UET","academyMethod":"Chính quy","levelOfAcademy":"Sinh viên","startedYear":"2018","schoolYearGroup":"K18","baseClass":"QH-2018","major":"Công nghệ thông tin"},
{"firstName":"Khoan","surName":"Phó Giáp","birthday":"1993-07-12","gender":"Nam","national":"Việt Nam","ethnic":"Mường","religion":"Không có","bornAddress":"198 Cầm Dương, Phi Lăng, Chu/Châu Quàng","homeAddress":"336 Ma Cống, Nông Đoạn, Thôi Ngọc","citizenCardId":"5196297588","currentAddress":"130 H’ma Quang, Thôi Diệp, Cổ Ninh","phoneNumber":"8621574461","email":"cgeertsenc@blogspot.com","fatherPhoneNumber":"8139846323","motherPhoneNumber":"6687310008","isEnlisted":false,"draftDate":"","school":"UET","academyMethod":"Chính quy","levelOfAcademy":"Sinh viên","startedYear":"2019","schoolYearGroup":"K19","baseClass":"CA-CLC-2019","major":"Công nghệ thông tin định hướng thị trường Nhật Bản"},
{"firstName":"Trưng","surName":"Diệp Khoa","birthday":"2005-12-13","gender":"Khác","national":"Việt Nam","ethnic":"Kinh","religion":"Không có","bornAddress":"163 Phù Viên, Phương Dư, Cát Ấu","homeAddress":"398 Tiêu Nghị, Chriêng Giàng, Kha Trương","citizenCardId":"4622064480","currentAddress":"464 Cảnh Thẩm, Ngọc Bảo, Âu Tiêu","phoneNumber":"4235750399","email":"mbaggerd@diigo.com","fatherPhoneNumber":"3297429404","motherPhoneNumber":"2392568579","isEnlisted":true,"draftDate":"2021-07-30","school":"UET","academyMethod":"Chính quy","levelOfAcademy":"Sinh viên","startedYear":"2013","schoolYearGroup":"K13","baseClass":"QH-2013","major":"Công nghệ thông tin định hướng thị trường Nhật Bản"},
{"firstName":"Ðổ","surName":"Lạc Mộc","birthday":"2002-01-24","gender":"Khác","national":"Nga","ethnic":"Kinh","religion":"Không có","bornAddress":"228 H’ma Đống, Tào Lãnh, Đương Đàm","homeAddress":"92 An Tào, Mộc Thành, Sái Âu","citizenCardId":"1585293091","currentAddress":"152 Khương Ma, La Hồng, Tuấn Cổ","phoneNumber":"5311900511","email":"allopise@latimes.com","fatherPhoneNumber":"5272858096","motherPhoneNumber":"2509696058","isEnlisted":true,"draftDate":"2021-10-23","school":"UET","academyMethod":"Chính quy","levelOfAcademy":"Sinh viên","startedYear":"2016","schoolYearGroup":"K16","baseClass":"CA-CLC-2016","major":"Kỹ thuật máy tính"},
{"firstName":"Cơ","surName":"Bành Vi","birthday":"1992-07-29","gender":"Khác","national":"Việt Nam","ethnic":"Kinh","religion":"Thiên Chúa giáo","bornAddress":"84 Thi Lỗ, Bành Hoàng, Tăng Cáp","homeAddress":"412 Đổng Thang, Quách Hùng, Thế Duy","citizenCardId":"4943844952","currentAddress":"23 Hoàng Vưu, Uông Cao, Tinh Vương","phoneNumber":"9494186428","email":"afrendf@amazon.com","fatherPhoneNumber":"8917173665","motherPhoneNumber":"2462117779","isEnlisted":false,"draftDate":"","school":"UET","academyMethod":"Chính quy","levelOfAcademy":"Sinh viên","startedYear":"2017","schoolYearGroup":"K17","baseClass":"QH-2017","major":"Công nghệ kỹ thuật xây dựng"},
{"firstName":"Nam","surName":"Nghiêm Hình","birthday":"1994-11-08","gender":"Nữ","national":"Việt Nam","ethnic":"Kinh","religion":"Không có","bornAddress":"21 Danh Thiều, Quản Bàng, Hề Cự","homeAddress":"102 Ma Quang, Thiều Giàng, Thi Ngụy","citizenCardId":"8360102074","currentAddress":"203 Chung Vương, Bành Bế, Quang Nhữ","phoneNumber":"7286846961","email":"frembrandtg@lulu.com","fatherPhoneNumber":"2795515496","motherPhoneNumber":"3164419707","isEnlisted":false,"draftDate":"","school":"UET","academyMethod":"Chính quy","levelOfAcademy":"Sinh viên","startedYear":"2008","schoolYearGroup":"K08","baseClass":"CA-CLC-2008","major":"Khoa Học Máy Tính"},
{"firstName":"Phàm","surName":"Ao Ca","birthday":"1996-06-17","gender":"Nam","national":"Việt Nam","ethnic":"Nùng","religion":"Không có","bornAddress":"491 Đồng Lâm, Phi Tôn, Đồng Lương","homeAddress":"161 Đặng Thịnh, Văn Đức, Ung Dư","citizenCardId":"8029817789","currentAddress":"314 Tòng Ngân, Nhữ Hàn, Trưng Đoàn","phoneNumber":"9643607011","email":"rjirieckh@4shared.com","fatherPhoneNumber":"6877416681","motherPhoneNumber":"4771239510","isEnlisted":true,"draftDate":"2019-02-22","school":"UET","academyMethod":"Chính quy","levelOfAcademy":"Sinh viên","startedYear":"2010","schoolYearGroup":"K10","baseClass":"QH-2010","major":"Công nghệ nông nghiệp"},
{"firstName":"Chú","surName":"Khai Thôi","birthday":"1993-07-16","gender":"Nam","national":"Việt Nam","ethnic":"Nùng","religion":"Không có","bornAddress":"223 Trác Chriêng, Thục Mùa, Thục Ân","homeAddress":"327 Chiêm Bảo, Đồng Bàng, Quang Yên","citizenCardId":"3740934883","currentAddress":"266 Tống Ưng, Trà Tri, Vương Võ","phoneNumber":"3328380048","email":"atinniswoodi@mapquest.com","fatherPhoneNumber":"5558040132","motherPhoneNumber":"2573299458","isEnlisted":true,"draftDate":"2019-08-15","school":"UET","academyMethod":"Chính quy","levelOfAcademy":"Sinh viên","startedYear":"2017","schoolYearGroup":"K17","baseClass":"CA-CLC-2017","major":"Khoa Học Máy Tính"},
{"firstName":"Bối","surName":"Đống Ngũ","birthday":"2005-06-20","gender":"Nữ","national":"Việt Nam","ethnic":"Mông","religion":"Không có","bornAddress":"248 Giàng Tô, Phùng Tinh, Thân Thẩm","homeAddress":"390 Hồ Điêu, Tiếp Lại, Phi Nhâm","citizenCardId":"4188805412","currentAddress":"81 Thập Bùi, Khoa Liên, Ngạc Hoàng","phoneNumber":"1263839377","email":"fgerdtsj@mysql.com","fatherPhoneNumber":"3963743704","motherPhoneNumber":"7912620419","isEnlisted":true,"draftDate":"2017-11-04","school":"UET","academyMethod":"Chính quy","levelOfAcademy":"Sinh viên","startedYear":"2011","schoolYearGroup":"K11","baseClass":"CA-CLC-2011","major":"Kỹ thuật năng lượng"},
{"firstName":"Huề","surName":"Hán Lỗ","birthday":"1997-10-27","gender":"Nam","national":"Việt Nam","ethnic":"Mường","religion":"Hòa Hảo","bornAddress":"55 Trà Thôi, Mầu/Màu Mục, Đồng Ánh","homeAddress":"478 Doãn Lãnh, Trương Nghiêm, Tông Nghiêm","citizenCardId":"2021855406","currentAddress":"15 Vạn Mùa, Ngũ Ân, Tri Nghiêm","phoneNumber":"8831262849","email":"cguidonik@seattletimes.com","fatherPhoneNumber":"1832224959","motherPhoneNumber":"1753501064","isEnlisted":true,"draftDate":"2019-12-13","school":"UET","academyMethod":"Chính quy","levelOfAcademy":"Sinh viên đã tốt nghiệp","startedYear":"2017","schoolYearGroup":"K17","baseClass":"QH-2017","major":"Mạng máy tính và truyền thông dữ liệu"},
{"firstName":"Ðiềm","surName":"Mâu Tòng","birthday":"1998-04-12","gender":"Nam","national":"Việt Nam","ethnic":"Kinh","religion":"Không có","bornAddress":"368 Đái Mùa, Cung Hứa, Hồng Lỗ","homeAddress":"304 Thiều Trác, Đinh Biện, Tào Từ","citizenCardId":"6255941167","currentAddress":"62 Kim Thịnh, Hề Hầu, Kiều Thiều","phoneNumber":"7359554984","email":"lsethl@ezinearticles.com","fatherPhoneNumber":"7449740906","motherPhoneNumber":"9322483148","isEnlisted":true,"draftDate":"2021-06-21","school":"UET","academyMethod":"Chính quy","levelOfAcademy":"Thạc sĩ","startedYear":"2012","schoolYearGroup":"K12","baseClass":"QH-2012","major":"Công nghệ thông tin"},
{"firstName":"Nội","surName":"Chiêm Thẩm","birthday":"1997-03-18","gender":"Nữ","national":"Việt Nam","ethnic":"Kinh","religion":"Hòa Hảo","bornAddress":"241 Uông Duy, Bàng H’, Tòng Ninh","homeAddress":"214 Sùng Đậu, Tri Nhâm, Lục Thất","citizenCardId":"2727705913","currentAddress":"197 Tăng Đường, Ưng Hồ, Khương Phù","phoneNumber":"5025700114","email":"bforsaithm@mysql.com","fatherPhoneNumber":"1177295803","motherPhoneNumber":"1517151077","isEnlisted":true,"draftDate":"2019-06-26","school":"UET","academyMethod":"Chính quy","levelOfAcademy":"Sinh viên","startedYear":"2019","schoolYearGroup":"K19","baseClass":"CA-CLC-2019","major":"Công nghệ kỹ thuật cơ điện tử"},
{"firstName":"Bộ","surName":"Viêm Ánh","birthday":"2001-12-30","gender":"Nam","national":"Việt Nam","ethnic":"Kinh","religion":"Hòa Hảo","bornAddress":"240 Hạ Ngạc, Hán H’, Thân Ưng","homeAddress":"493 Thất Trình, Hàn Lư, Tào Phương","citizenCardId":"2849432636","currentAddress":"459 Chử Viêm, La Thiều, Tiêu Đường","phoneNumber":"1692051225","email":"hellerkern@cam.ac.uk","fatherPhoneNumber":"6041004631","motherPhoneNumber":"8571515701","isEnlisted":true,"draftDate":"2017-10-27","school":"UET","academyMethod":"Chính quy","levelOfAcademy":"Sinh viên","startedYear":"2011","schoolYearGroup":"K11","baseClass":"QH-2011","major":"Kỹ thuật Robot"},
{"firstName":"Bồng","surName":"Nguyễn Hà","birthday":"1997-11-26","gender":"Nam","national":"Việt Nam","ethnic":"Nùng","religion":"Phật giáo","bornAddress":"331 Đồng Lèng, Phạm Tuấn, An Hùng","homeAddress":"301 Sùng Ngũ, H’ Dương, Đôn H’ma","citizenCardId":"2944515055","currentAddress":"425 Đoàn Danh, Lộ Nghị, Thiều Cù","phoneNumber":"9951241184","email":"tlindero@gnu.org","fatherPhoneNumber":"3531572914","motherPhoneNumber":"3921820664","isEnlisted":false,"draftDate":"","school":"UET","academyMethod":"Chính quy","levelOfAcademy":"Sinh viên","startedYear":"2012","schoolYearGroup":"K12","baseClass":"CA-CLC-2012","major":"Kỹ thuật Robot"},
{"firstName":"Lăng","surName":"La Lộ","birthday":"2000-11-30","gender":"Nữ","national":"Việt Nam","ethnic":"Nùng","religion":"Hồi giáo","bornAddress":"123 Hán Thang, H’nia Diêm, Đôn Ngạc","homeAddress":"216 Tông Bàng, Ánh Thành, Lã Ty","citizenCardId":"2514288045","currentAddress":"410 Ánh Mâu, Ninh Chriêng, Đổng Nông","phoneNumber":"4727448463","email":"ddoumerp@sfgate.com","fatherPhoneNumber":"8108032344","motherPhoneNumber":"2475215923","isEnlisted":false,"draftDate":"","school":"UET","academyMethod":"Chính quy","levelOfAcademy":"Sinh viên","startedYear":"2007","schoolYearGroup":"K07","baseClass":"CA-CLC-2007","major":"Công nghệ kỹ thuật cơ điện tử"},
{"firstName":"Ðỉnh","surName":"Lều Đỗ","birthday":"1998-05-19","gender":"Khác","national":"Việt Nam","ethnic":"Kinh","religion":"Tin Lành","bornAddress":"172 Hi Quàng, Hề Hồng, Khiếu Đậu","homeAddress":"201 Thoa Dư, Thân Viên, H’nia Ấu","citizenCardId":"7941347539","currentAddress":"496 Phạm Bạch, Tri Nguyễn, Bình Hàn","phoneNumber":"3198144718","email":"phalheadq@a8.net","fatherPhoneNumber":"9831983249","motherPhoneNumber":"3069306850","isEnlisted":false,"draftDate":"","school":"UET","academyMethod":"Chính quy","levelOfAcademy":"Sinh viên đã tốt nghiệp","startedYear":"2012","schoolYearGroup":"K12","baseClass":"CA-CLC-2012","major":"Kỹ thuật điều khiển và tự động hóa"},
{"firstName":"Chỉ","surName":"H’nia Thôi","birthday":"2001-02-27","gender":"Nữ","national":"Việt Nam","ethnic":"Kinh","religion":"Không có","bornAddress":"125 Đoàn Điêu, Mâu Ngô, Ân Lò","homeAddress":"78 Đăng Ngọc, Thoa Bì, Vưu Sử","citizenCardId":"9216584777","currentAddress":"358 Đặng Giáp, Phó Giáp, Dương Lê","phoneNumber":"4379731744","email":"blyddiattr@google.com.au","fatherPhoneNumber":"7719564202","motherPhoneNumber":"6955473191","isEnlisted":true,"draftDate":"2020-02-20","school":"UET","academyMethod":"Chính quy","levelOfAcademy":"Sinh viên đã tốt nghiệp","startedYear":"2014","schoolYearGroup":"K14","baseClass":"QH-2014","major":"Công nghệ nông nghiệp"},
{"firstName":"Học","surName":"Hầu Đôn","birthday":"1992-07-06","gender":"Nữ","national":"Việt Nam","ethnic":"Thái","religion":"Hòa Hảo","bornAddress":"72 Tào Tuấn, Thập Kha, Hoa Uông","homeAddress":"478 Tôn Đầu, Ong Điền, Điều Phạm","citizenCardId":"9712221407","currentAddress":"237 Tề Hề, Bế Sùng, Yên Hồng","phoneNumber":"5678532573","email":"dgreedings@reddit.com","fatherPhoneNumber":"7748048435","motherPhoneNumber":"6789619218","isEnlisted":false,"draftDate":"","school":"UET","academyMethod":"Chính quy","levelOfAcademy":"Sinh viên","startedYear":"2013","schoolYearGroup":"K13","baseClass":"CA-CLC-2013","major":"Khoa Học Máy Tính"},
{"firstName":"Liễn","surName":"Phan Hồ","birthday":"1993-01-28","gender":"Nam","national":"Việt Nam","ethnic":"Mông","religion":"Hồi giáo","bornAddress":"408 Lèng Lý, Anh Nghiêm, Bảo Bạch","homeAddress":"389 Kiều Khúc, Thục Trương, Đường Tôn","citizenCardId":"1417170816","currentAddress":"435 Hoa Uông, Thân Lưu, Cảnh Ưng","phoneNumber":"1632332597","email":"dmacgregort@phpbb.com","fatherPhoneNumber":"8029464170","motherPhoneNumber":"4408051622","isEnlisted":true,"draftDate":"2018-12-31","school":"UET","academyMethod":"Chính quy","levelOfAcademy":"Sinh viên","startedYear":"2010","schoolYearGroup":"K10","baseClass":"CA-CLC-2010","major":"Khoa Học Máy Tính"},
{"firstName":"Thâu","surName":"Vạn Xa","birthday":"1991-08-17","gender":"Nữ","national":"Việt Nam","ethnic":"Kinh","religion":"Không có","bornAddress":"357 Mạch Chriêng, Đỗ Chương, Cù Đoạn","homeAddress":"314 Lư Đoàn, Bá Hoa, Duy Bá","citizenCardId":"4005682014","currentAddress":"386 Hoa Thập, Cấn Vi, Thập Ninh","phoneNumber":"5417894140","email":"wnisbyu@columbia.edu","fatherPhoneNumber":"9977961987","motherPhoneNumber":"4679577650","isEnlisted":true,"draftDate":"2018-08-25","school":"UET","academyMethod":"Chính quy","levelOfAcademy":"Sinh viên","startedYear":"2011","schoolYearGroup":"K11","baseClass":"QH-2011","major":"Kỹ thuật máy tính"},
{"firstName":"Bạt","surName":"Tán Mạc","birthday":"2003-12-25","gender":"Nữ","national":"Việt Nam","ethnic":"Kinh","religion":"Không có","bornAddress":"269 Cồ Lư, Ngụy Bình, Dương Tán","homeAddress":"31 Vương H’, Quách Ứng, Hi Bàng","citizenCardId":"8939810090","currentAddress":"257 Mang Bì, Tấn Doãn, Dương Tông","phoneNumber":"9424498222","email":"messeryv@themeforest.net","fatherPhoneNumber":"3851795348","motherPhoneNumber":"7321388908","isEnlisted":true,"draftDate":"2017-04-28","school":"UET","academyMethod":"Chính quy","levelOfAcademy":"Sinh viên","startedYear":"2014","schoolYearGroup":"K14","baseClass":"CA-CLC-2014","major":"Kỹ thuật điều khiển và tự động hóa"},
{"firstName":"Ðính","surName":"Tấn Cầm","birthday":"2001-11-06","gender":"Nam","national":"Việt Nam","ethnic":"Tày","religion":"Không có","bornAddress":"326 Tào Cồ, Thi Nhan, Liêu Chúng","homeAddress":"96 Lều Dư, Trình Đổng, Thẩm Ngô","citizenCardId":"9972462188","currentAddress":"111 Vưu Kim, Lò Sử, Đầu Tô","phoneNumber":"1021926882","email":"jpopplewellw@boston.com","fatherPhoneNumber":"4601624521","motherPhoneNumber":"2344645287","isEnlisted":true,"draftDate":"2016-01-07","school":"UET","academyMethod":"Chính quy","levelOfAcademy":"Sinh viên","startedYear":"2018","schoolYearGroup":"K18","baseClass":"CA-CLC-2018","major":"Kỹ thuật điều khiển và tự động hóa"},
{"firstName":"Dực","surName":"Sầm Hùng","birthday":"1997-08-04","gender":"Khác","national":"Việt Nam","ethnic":"Thái","religion":"Không có","bornAddress":"483 Tôn Tán, Nghị Thành, Mục Tấn","homeAddress":"494 Đức Âu, Thoa Bành, Trang Phương","citizenCardId":"9218597302","currentAddress":"9 Đặng Hoa, Tri Bảo, Cảnh Đoàn","phoneNumber":"8283722785","email":"dmaclaigx@elegantthemes.com","fatherPhoneNumber":"9475085574","motherPhoneNumber":"5563711751","isEnlisted":false,"draftDate":"","school":"UET","academyMethod":"Chính quy","levelOfAcademy":"Thạc sĩ","startedYear":"2008","schoolYearGroup":"K08","baseClass":"CA-CLC-2008","major":"Kỹ thuật máy tính"},
{"firstName":"Xuyến","surName":"Tống Ấu","birthday":"1994-12-05","gender":"Nam","national":"Việt Nam","ethnic":"Mông","religion":"Không có","bornAddress":"255 An Đầu, Ung Công, Đôn Sử","homeAddress":"152 Cát Nhan, Bành An, Cự Cam","citizenCardId":"9350558920","currentAddress":"295 Mẫn Đàm, Cồ Ngô, Chử Đèo","phoneNumber":"4718466665","email":"eklimpty@pen.io","fatherPhoneNumber":"4968063122","motherPhoneNumber":"5887712498","isEnlisted":false,"draftDate":"","school":"UET","academyMethod":"Chính quy","levelOfAcademy":"Sinh viên","startedYear":"2006","schoolYearGroup":"K06","baseClass":"QH-2006","major":"Công nghệ kỹ thuật xây dựng"},
{"firstName":"Cứ","surName":"Đức Cồ","birthday":"2004-03-31","gender":"Nam","national":"Việt Nam","ethnic":"Mường","religion":"Không có","bornAddress":"181 Phó Thân, La Trà, Lạc Lỗ","homeAddress":"96 Trịnh Thịnh, Phùng Mâu, Ngọ Hồ","citizenCardId":"3758536111","currentAddress":"269 Anh Khai, Sơn Viêm, Phú Tiêu","phoneNumber":"3909751921","email":"dhrinchenkoz@cmu.edu","fatherPhoneNumber":"6289572943","motherPhoneNumber":"2273540492","isEnlisted":true,"draftDate":"2017-01-07","school":"UET","academyMethod":"Chính quy","levelOfAcademy":"Sinh viên đã tốt nghiệp","startedYear":"2015","schoolYearGroup":"K15","baseClass":"QH-2015","major":"Công nghệ Hàng không vũ trụ"},
{"firstName":"Thước","surName":"Lại Ông","birthday":"1999-07-21","gender":"Nam","national":"Nhật","ethnic":"Kinh","religion":"Không có","bornAddress":"117 H’ma Thôi, Đèo Tinh, Sùng H’ma","homeAddress":"436 Đái H’, Phi Lý, Quang Mục","citizenCardId":"8409767686","currentAddress":"426 Khương Liêu, Lộ Hướng, Cáp Đăng","phoneNumber":"1523062782","email":"skording10@arstechnica.com","fatherPhoneNumber":"7635799783","motherPhoneNumber":"9339255025","isEnlisted":true,"draftDate":"2018-12-18","school":"UET","academyMethod":"Chính quy","levelOfAcademy":"Sinh viên đã tốt nghiệp","startedYear":"2009","schoolYearGroup":"K09","baseClass":"CA-CLC-2009","major":"Công nghệ thông tin định hướng thị trường Nhật Bản"},
{"firstName":"Cửu","surName":"Ao Liên","birthday":"2002-02-13","gender":"Nữ","national":"Mỹ","ethnic":"Mông","religion":"Không có","bornAddress":"253 Bình Lưu, Lò Phi, Kiều Lô","homeAddress":"358 Tuấn Ninh, Đường Bảo, Tăng Thi","citizenCardId":"5552009541","currentAddress":"356 Thái Lê, Xung Bì, Nhữ Uông","phoneNumber":"8626996843","email":"mcullingford11@csmonitor.com","fatherPhoneNumber":"8347943140","motherPhoneNumber":"1081823417","isEnlisted":true,"draftDate":"2017-04-13","school":"UET","academyMethod":"Chính quy","levelOfAcademy":"Sinh viên","startedYear":"2012","schoolYearGroup":"K12","baseClass":"QH-2012","major":"Mạng máy tính và truyền thông dữ liệu"},
{"firstName":"Ninh","surName":"Kiều Ty","birthday":"2004-08-29","gender":"Khác","national":"Việt Nam","ethnic":"Nùng","religion":"Thiên Chúa giáo","bornAddress":"35 Lăng Điền, Quách Mã, Thịnh Từ","homeAddress":"55 Trà Phan, Đào Bùi, Phùng Tạ","citizenCardId":"2468168321","currentAddress":"177 Thành Cầm, Điêu La, Ngụy Bồ","phoneNumber":"6395426822","email":"pszymanowicz12@wix.com","fatherPhoneNumber":"8079398983","motherPhoneNumber":"7251777060","isEnlisted":false,"draftDate":"","school":"UET","academyMethod":"Chính quy","levelOfAcademy":"Sinh viên","startedYear":"2010","schoolYearGroup":"K10","baseClass":"CA-CLC-2010","major":"Cơ kỹ thuật"},
{"firstName":"Ðoái","surName":"Khúc Đồng","birthday":"1996-06-08","gender":"Nam","national":"Việt Nam","ethnic":"Kinh","religion":"Không có","bornAddress":"232 Lục Mang, Cồ Thẩm, Tấn Ngân","homeAddress":"441 Đổng Lạc, Lại Danh, Bành Anh","citizenCardId":"5057463519","currentAddress":"286 Cầm Bình, Doãn Nghiêm, Tôn Đổng","phoneNumber":"8108961367","email":"gatley13@thetimes.co.uk","fatherPhoneNumber":"3319588553","motherPhoneNumber":"4454701551","isEnlisted":false,"draftDate":"","school":"UET","academyMethod":"Chính quy","levelOfAcademy":"Sinh viên","startedYear":"2020","schoolYearGroup":"K20","baseClass":"CA-CLC-2020","major":"Công nghệ thông tin định hướng thị trường Nhật Bản"},
{"firstName":"Mầu","surName":"Bảo Hoàng","birthday":"1991-10-14","gender":"Nam","national":"Việt Nam","ethnic":"Kinh","religion":"Không có","bornAddress":"431 Lô Ma, Bàng Dương, Bồ Xa","homeAddress":"20 Kông Bá, Khổng Hình, Cù Lê","citizenCardId":"9333663932","currentAddress":"309 Hứa Luyện, Ung Kiểu, Ấu Ân","phoneNumber":"1788759821","email":"pweller14@about.me","fatherPhoneNumber":"6326960398","motherPhoneNumber":"4571038743","isEnlisted":true,"draftDate":"2021-03-05","school":"UET","academyMethod":"Chính quy","levelOfAcademy":"Sinh viên đã tốt nghiệp","startedYear":"2015","schoolYearGroup":"K15","baseClass":"QH-2015","major":"Công nghệ kỹ thuật cơ điện tử"},
{"firstName":"Tiềm","surName":"Lưu Khiếu","birthday":"1998-01-29","gender":"Nam","national":"Việt Nam","ethnic":"Kinh","religion":"Không có","bornAddress":"335 Sùng Phương, Âu Liễu, Khúc Khuất","homeAddress":"21 Phi Tiêu, Ao Cấn, Đồng Lăng","citizenCardId":"0286008645","currentAddress":"221 Lăng Ca, Thất Phạm, Uông Trang","phoneNumber":"4369096362","email":"hminor15@webeden.co.uk","fatherPhoneNumber":"6835919209","motherPhoneNumber":"4429490751","isEnlisted":false,"draftDate":"","school":"UET","academyMethod":"Chính quy","levelOfAcademy":"Sinh viên","startedYear":"2014","schoolYearGroup":"K14","baseClass":"CA-CLC-2014","major":"Cơ kỹ thuật"},
{"firstName":"Tường","surName":"Hoa Thang","birthday":"1993-09-21","gender":"Nam","national":"Việt Nam","ethnic":"Thái","religion":"Không có","bornAddress":"255 Kiều Mục, Hồ Triệu, Trương Kiểu","homeAddress":"94 Trang Cầm, Phó Quàng, Nghiêm Mâu","citizenCardId":"3285392053","currentAddress":"418 Phan Tuấn, Quàng Bình, Cồ Cam","phoneNumber":"6945793534","email":"fotson16@pbs.org","fatherPhoneNumber":"9657548362","motherPhoneNumber":"1148660379","isEnlisted":true,"draftDate":"2019-03-11","school":"UET","academyMethod":"Chính quy","levelOfAcademy":"Sinh viên","startedYear":"2011","schoolYearGroup":"K11","baseClass":"CA-CLC-2011","major":"Cơ kỹ thuật"},
{"firstName":"Ðào","surName":"Mạc Ngân","birthday":"1994-06-15","gender":"Nam","national":"Lào","ethnic":"Kinh","religion":"Không có","bornAddress":"371 Tuấn Từ, Công Cáp, Đống Lỗ","homeAddress":"239 Quang La, Mùa H’nia, Hạ Hình","citizenCardId":"0175368791","currentAddress":"128 Lèng Cái, Hạ Bàn, Thang Ung","phoneNumber":"5263644504","email":"clenormand17@shop-pro.jp","fatherPhoneNumber":"3017631413","motherPhoneNumber":"4873605149","isEnlisted":false,"draftDate":"","school":"UET","academyMethod":"Chính quy","levelOfAcademy":"Sinh viên","startedYear":"2019","schoolYearGroup":"K19","baseClass":"QH-2019","major":"Công nghệ kỹ thuật cơ điện tử"},
{"firstName":"Ân","surName":"Lò Tán","birthday":"1996-11-19","gender":"Nữ","national":"Việt Nam","ethnic":"Tày","religion":"Không có","bornAddress":"363 Cồ Thoa, Cao Phó, Hề Trình","homeAddress":"215 Đồng Mã, Phi Trình, Hạ Kông","citizenCardId":"7818505822","currentAddress":"481 Giao Khai, Ân Lương, Nhữ Thục","phoneNumber":"9848864578","email":"gdixcey18@cpanel.net","fatherPhoneNumber":"6157717238","motherPhoneNumber":"9052378322","isEnlisted":false,"draftDate":"","school":"UET","academyMethod":"Chính quy","levelOfAcademy":"Sinh viên","startedYear":"2017","schoolYearGroup":"K17","baseClass":"QH-2017","major":"Công nghệ thông tin"},
{"firstName":"Tất","surName":"Bàn Bế","birthday":"1995-03-22","gender":"Nữ","national":"Nhật","ethnic":"Kinh","religion":"Không có","bornAddress":"484 Bì Chế, Khương Đỗ, Vi Đăng","homeAddress":"349 Phạm Đồ, Tiếp Hàn, Lâm Lăng","citizenCardId":"5606712202","currentAddress":"172 Mầu/Màu Thi, Lều Thoa, Viên Xung","phoneNumber":"4299034519","email":"wprint19@tamu.edu","fatherPhoneNumber":"4297010117","motherPhoneNumber":"1114514827","isEnlisted":true,"draftDate":"2018-03-09","school":"UET","academyMethod":"Chính quy","levelOfAcademy":"Sinh viên đã tốt nghiệp","startedYear":"2018","schoolYearGroup":"K18","baseClass":"CA-CLC-2018","major":"Công nghệ kỹ thuật xây dựng"},
{"firstName":"Lam","surName":"Ao Trần","birthday":"1995-09-18","gender":"Nữ","national":"Việt Nam","ethnic":"Mông","religion":"Không có","bornAddress":"450 Giàng Huỳnh, Phù Bành, Kiều Bì","homeAddress":"24 Ưng Mai, Tiêu Lyly, Mộc Phạm","citizenCardId":"0084293306","currentAddress":"163 Vạn Liễu, Hạ Chriêng, Ty Ứng","phoneNumber":"6988605292","email":"dpearcy1a@com.com","fatherPhoneNumber":"4985361017","motherPhoneNumber":"5615632290","isEnlisted":false,"draftDate":"","school":"UET","academyMethod":"Chính quy","levelOfAcademy":"Sinh viên","startedYear":"2007","schoolYearGroup":"K07","baseClass":"CA-CLC-2007","major":"Công nghệ nông nghiệp"},
{"firstName":"Cai","surName":"Tăng Ung","birthday":"2003-10-31","gender":"Nam","national":"Việt Nam","ethnic":"Kinh","religion":"Không có","bornAddress":"47 Ứng Hi, Cù Lô, Lộ Đậu","homeAddress":"322 Trà Mùa, Ấu Phạm, Công Tiếp","citizenCardId":"9662497218","currentAddress":"431 Khoa Liễu, Hồng Thục, Đào H’nia","phoneNumber":"5167278614","email":"fblandford1b@quantcast.com","fatherPhoneNumber":"9871667217","motherPhoneNumber":"4827244962","isEnlisted":true,"draftDate":"2017-07-04","school":"UET","academyMethod":"Chính quy","levelOfAcademy":"Sinh viên đã tốt nghiệp","startedYear":"2008","schoolYearGroup":"K08","baseClass":"CA-CLC-2008","major":"Kỹ thuật năng lượng"},
{"firstName":"Truyền","surName":"Ca Chriêng","birthday":"1998-12-31","gender":"Nam","national":"Việt Nam","ethnic":"Mông","religion":"Không có","bornAddress":"288 Lại Cáp, H’ma Sơn, Uông Bạc","homeAddress":"206 Thái Trưng, Tinh Nguyễn, Nghiêm Lò","citizenCardId":"3282698798","currentAddress":"268 Bình Hoàng, Chương Kiểu, Hứa Hồng","phoneNumber":"5822891587","email":"pkillelea1c@youtube.com","fatherPhoneNumber":"9132454239","motherPhoneNumber":"4423548966","isEnlisted":false,"draftDate":"","school":"UET","academyMethod":"Chính quy","levelOfAcademy":"Sinh viên","startedYear":"2009","schoolYearGroup":"K09","baseClass":"QH-2009","major":"Điện Tử Viễn Thông"},
{"firstName":"Nghiệp","surName":"Tri Đổng","birthday":"2003-02-24","gender":"Nữ","national":"Việt Nam","ethnic":"Mông","religion":"Không có","bornAddress":"335 Thoa Đoàn, H’ma Phi, Lã Nguyễn","homeAddress":"386 Chu/Châu Hồng, Khúc Lăng, Biện Hạ","citizenCardId":"4451451205","currentAddress":"270 Dư Đồ, Hồng Đôn, Lục Cam","phoneNumber":"9815470070","email":"jmccomas1d@timesonline.co.uk","fatherPhoneNumber":"7652694732","motherPhoneNumber":"5324257477","isEnlisted":true,"draftDate":"2020-04-18","school":"UET","academyMethod":"Chính quy","levelOfAcademy":"Sinh viên đã tốt nghiệp","startedYear":"2006","schoolYearGroup":"K06","baseClass":"QH-2006","major":"Kỹ thuật điều khiển và tự động hóa"},
{"firstName":"Thư","surName":"Ứng Kha","birthday":"1991-05-09","gender":"Nam","national":"Việt Nam","ethnic":"Mường","religion":"Tin Lành","bornAddress":"26 Đương Ninh, Danh Quàng, Đồ Công","homeAddress":"285 Bành Chương, Xa Sơn, Vi Dương","citizenCardId":"1693622971","currentAddress":"328 Dương Ngạc, Thôi Bạc, Khổng Mâu","phoneNumber":"7502051018","email":"bhobble1e@berkeley.edu","fatherPhoneNumber":"2964341235","motherPhoneNumber":"5357270560","isEnlisted":false,"draftDate":"","school":"UET","academyMethod":"Chính quy","levelOfAcademy":"Sinh viên","startedYear":"2016","schoolYearGroup":"K16","baseClass":"CA-CLC-2016","major":"Kỹ thuật điều khiển và tự động hóa"},
{"firstName":"Thứ","surName":"Tiêu Ninh","birthday":"2000-12-08","gender":"Nữ","national":"Việt Nam","ethnic":"Nùng","religion":"Phật giáo","bornAddress":"75 Kiểu Trần, Đức Tuấn, Ngũ La","homeAddress":"467 Danh Hầu, Kha Lưu, Lư Ứng","citizenCardId":"7960656916","currentAddress":"22 Giàng Lý, Cai Ưng, Lâm Sùng","phoneNumber":"7966309474","email":"gpeschke1f@xrea.com","fatherPhoneNumber":"3106729626","motherPhoneNumber":"1835568766","isEnlisted":false,"draftDate":"","school":"UET","academyMethod":"Chính quy","levelOfAcademy":"Sinh viên đã tốt nghiệp","startedYear":"2015","schoolYearGroup":"K15","baseClass":"CA-CLC-2015","major":"Hệ thống thông tin"},
{"firstName":"Vân","surName":"Lý Khu","birthday":"1996-06-18","gender":"Nam","national":"Việt Nam","ethnic":"Thái","religion":"Phật giáo","bornAddress":"359 Chương Linh, Thế Hán, Lý Bồ","homeAddress":"23 Xa Diêm, Trịnh Thục, Hồ Mang","citizenCardId":"8183081177","currentAddress":"227 Vương Ân, Lăng Tòng, Ma Khoa","phoneNumber":"1758045637","email":"jmallender1g@paypal.com","fatherPhoneNumber":"7739337146","motherPhoneNumber":"3938657283","isEnlisted":false,"draftDate":"","school":"UET","academyMethod":"Chính quy","levelOfAcademy":"Thạc sĩ","startedYear":"2015","schoolYearGroup":"K15","baseClass":"QH-2015","major":"Điện Tử Viễn Thông"},
{"firstName":"Lãm","surName":"Ma Cát","birthday":"1995-02-17","gender":"Khác","national":"Việt Nam","ethnic":"Kinh","religion":"Không có","bornAddress":"50 Mai Dư, Tiêu Ân, Trương Tiếp","homeAddress":"401 Khu Hùng, Giả Tào, Sùng Tấn","citizenCardId":"1450073794","currentAddress":"305 Lạc Cống, Vi Lâm, Cổ Điêu","phoneNumber":"9623264464","email":"rlanfranconi1h@csmonitor.com","fatherPhoneNumber":"2652120500","motherPhoneNumber":"8118783945","isEnlisted":true,"draftDate":"2019-06-19","school":"UET","academyMethod":"Chính quy","levelOfAcademy":"Sinh viên","startedYear":"2011","schoolYearGroup":"K11","baseClass":"CA-CLC-2011","major":"Khoa Học Máy Tính"},
{"firstName":"Cán","surName":"Quách Bảo","birthday":"2005-02-14","gender":"Nam","national":"Việt Nam","ethnic":"Mường","religion":"Không có","bornAddress":"131 Hán Dương, Sử Khâu, Hùng Khoa","homeAddress":"255 Viên Thái, Cáp Dã, Chử Ngũ","citizenCardId":"4744303943","currentAddress":"15 Mạch Từ, Ngọ Cồ, Chriêng Đỗ","phoneNumber":"9463650644","email":"ppeterken1i@networkadvertising.org","fatherPhoneNumber":"2996440449","motherPhoneNumber":"1375457029","isEnlisted":false,"draftDate":"","school":"UET","academyMethod":"Chính quy","levelOfAcademy":"Sinh viên","startedYear":"2018","schoolYearGroup":"K18","baseClass":"CA-CLC-2018","major":"Kỹ thuật năng lượng"},
{"firstName":"Cảnh","surName":"Nguyễn Tuấn","birthday":"1991-04-23","gender":"Nữ","national":"Việt Nam","ethnic":"Kinh","religion":"Không có","bornAddress":"407 Viên Thi, Lý Phi, Khoa Bạch","homeAddress":"489 Trác Thang, Công Sơn, Luyện Lỗ","citizenCardId":"8003449464","currentAddress":"465 Thất Linh, Thào Võ, Đồ Ngân","phoneNumber":"4468457418","email":"gosgorby1j@elegantthemes.com","fatherPhoneNumber":"6654992046","motherPhoneNumber":"4719172646","isEnlisted":true,"draftDate":"2021-06-11","school":"UET","academyMethod":"Chính quy","levelOfAcademy":"Sinh viên","startedYear":"2020","schoolYearGroup":"K20","baseClass":"QH-2020","major":"Công nghệ kỹ thuật xây dựng"},
{"firstName":"Nhân","surName":"Hầu Đăng","birthday":"2002-02-09","gender":"Nam","national":"Việt Nam","ethnic":"Mường","religion":"Không có","bornAddress":"319 Tiêu Hứa, Cù Thịnh, Quản Mùa","homeAddress":"361 Văn Sơn, Sùng Lò, Bồ Tống","citizenCardId":"5633225848","currentAddress":"38 Lê Kông, Vạn Mùa, Đương Khiếu","phoneNumber":"8537297309","email":"gscarce1k@symantec.com","fatherPhoneNumber":"6716525386","motherPhoneNumber":"6211975973","isEnlisted":false,"draftDate":"","school":"UET","academyMethod":"Chính quy","levelOfAcademy":"Sinh viên","startedYear":"2014","schoolYearGroup":"K14","baseClass":"CA-CLC-2014","major":"Kỹ thuật Robot"},
{"firstName":"Tiên","surName":"Triệu Đoàn","birthday":"1996-01-10","gender":"Nam","national":"Việt Nam","ethnic":"Tày","religion":"Không có","bornAddress":"188 Bạch Ngạc, Lãnh Tôn, Trưng Tuấn","homeAddress":"269 Chúng Trần, Bế Bùi, Mâu Thào","citizenCardId":"0315299002","currentAddress":"189 Phú Đoàn, Tiếp Mâu, Tri Phạm","phoneNumber":"7007195340","email":"drayne1l@oakley.com","fatherPhoneNumber":"7731330989","motherPhoneNumber":"2164938343","isEnlisted":false,"draftDate":"","school":"UET","academyMethod":"Chính quy","levelOfAcademy":"Sinh viên","startedYear":"2008","schoolYearGroup":"K08","baseClass":"QH-2008","major":"Công nghệ thông tin"},
{"firstName":"Lãnh","surName":"Chúng Thế","birthday":"2001-10-07","gender":"Nam","national":"Nhật","ethnic":"Tày","religion":"Không có","bornAddress":"103 Tào Đàm, Liên Anh, Sử Duy","homeAddress":"433 Cổ Cao, Lãnh Lò, Tăng Lâm","citizenCardId":"1371194483","currentAddress":"481 H’ Ngô, Ngô Phù, Bạch Ngân","phoneNumber":"8923836070","email":"hbradock1m@tuttocitta.it","fatherPhoneNumber":"4617756603","motherPhoneNumber":"4175636731","isEnlisted":false,"draftDate":"","school":"UET","academyMethod":"Chính quy","levelOfAcademy":"Sinh viên","startedYear":"2011","schoolYearGroup":"K11","baseClass":"CA-CLC-2011","major":"Công nghệ thông tin định hướng thị trường Nhật Bản"},
{"firstName":"Quảng","surName":"Mục Công","birthday":"1995-12-14","gender":"Nam","national":"Việt Nam","ethnic":"Kinh","religion":"Không có","bornAddress":"282 Hoàng Võ, Nghiêm Hồ, Điêu Từ","homeAddress":"165 Nghị Cáp, Ánh Triệu, Đới Hoa","citizenCardId":"8872090482","currentAddress":"226 Đái Lãnh, Viêm Ấu, Bùi Mầu/Màu","phoneNumber":"1025990901","email":"rhasslocher1n@forbes.com","fatherPhoneNumber":"5215887940","motherPhoneNumber":"4707454780","isEnlisted":false,"draftDate":"","school":"UET","academyMethod":"Chính quy","levelOfAcademy":"Sinh viên đã tốt nghiệp","startedYear":"2015","schoolYearGroup":"K15","baseClass":"CA-CLC-2015","major":"Công nghệ thông tin"},
{"firstName":"Tống","surName":"Lăng Dương","birthday":"1995-09-13","gender":"Nam","national":"Việt Nam","ethnic":"Kinh","religion":"Hồi giáo","bornAddress":"22 Trần Khương, Khai Khoa, Nghị Đồ","homeAddress":"75 Ninh Lư, Thạch Đống, Sơn Hi","citizenCardId":"3385233909","currentAddress":"299 Phi Mạnh, Lèng Trưng, Mã Huỳnh","phoneNumber":"6825205820","email":"nmeir1o@diigo.com","fatherPhoneNumber":"8335456443","motherPhoneNumber":"5718720726","isEnlisted":true,"draftDate":"2020-05-01","school":"UET","academyMethod":"Chính quy","levelOfAcademy":"Sinh viên đã tốt nghiệp","startedYear":"2018","schoolYearGroup":"K18","baseClass":"QH-2018","major":"Kỹ thuật năng lượng"},
{"firstName":"Vị","surName":"Viêm An","birthday":"2001-12-20","gender":"Nam","national":"Việt Nam","ethnic":"Kinh","religion":"Không có","bornAddress":"68 Bạch Bùi, Khai Kim, Quang Trác","homeAddress":"279 Đinh Mã, Sùng Uông, Khương Bá","citizenCardId":"1735615455","currentAddress":"107 Vi Đái, Mã Ngũ, Kiều Nông","phoneNumber":"2983923191","email":"amounch1p@house.gov","fatherPhoneNumber":"7351845643","motherPhoneNumber":"6519124431","isEnlisted":true,"draftDate":"2020-12-05","school":"UET","academyMethod":"Chính quy","levelOfAcademy":"Sinh viên","startedYear":"2010","schoolYearGroup":"K10","baseClass":"QH-2010","major":"Kỹ thuật năng lượng"},
{"firstName":"Giáp","surName":"Hán Thạch","birthday":"1994-07-31","gender":"Nữ","national":"Việt Nam","ethnic":"Kinh","religion":"Không có","bornAddress":"228 Ngô Duy, Mang Ninh, Chung Sơn","homeAddress":"183 Khà Vũ, Cảnh Tăng, Xung Tôn","citizenCardId":"9551399889","currentAddress":"124 Bình Thân, Đăng Từ, Khúc Bàng","phoneNumber":"5917395294","email":"mgleed1q@dyndns.org","fatherPhoneNumber":"1965154955","motherPhoneNumber":"2535290838","isEnlisted":false,"draftDate":"","school":"UET","academyMethod":"Chính quy","levelOfAcademy":"Sinh viên","startedYear":"2014","schoolYearGroup":"K14","baseClass":"CA-CLC-2014","major":"Điện Tử Viễn Thông"},
{"firstName":"Cửu","surName":"Hứa Khổng","birthday":"2004-04-18","gender":"Nam","national":"Việt Nam","ethnic":"Thái","religion":"Tin Lành","bornAddress":"426 La Anh, Mai Tuấn, Đỗ Nhâm","homeAddress":"246 Vũ Đống, Linh Cam, Đậu Luyện","citizenCardId":"2598838122","currentAddress":"452 Kiểu Hồ, Nông Khiếu, Ung Cầm","phoneNumber":"8288299738","email":"jmulvenna1r@linkedin.com","fatherPhoneNumber":"6562026949","motherPhoneNumber":"5415290698","isEnlisted":false,"draftDate":"","school":"UET","academyMethod":"Chính quy","levelOfAcademy":"Sinh viên","startedYear":"2020","schoolYearGroup":"K20","baseClass":"CA-CLC-2020","major":"Kỹ thuật Robot"},
{"firstName":"Keo","surName":"Phó Trương","birthday":"1990-11-27","gender":"Khác","national":"Việt Nam","ethnic":"Mông","religion":"Không có","bornAddress":"239 Trà Mai, Khương Hàn, Vưu Lộ","homeAddress":"154 Ánh H’ma, Duy Ngạc, Cù Thập","citizenCardId":"6076839910","currentAddress":"158 Trác Thào, Văn Liễu, Ấu Cồ","phoneNumber":"6646412022","email":"vtubritt1s@bloomberg.com","fatherPhoneNumber":"1654257430","motherPhoneNumber":"9247159295","isEnlisted":true,"draftDate":"2020-01-27","school":"UET","academyMethod":"Chính quy","levelOfAcademy":"Thạc sĩ","startedYear":"2007","schoolYearGroup":"K07","baseClass":"CA-CLC-2007","major":"Cơ kỹ thuật"},
{"firstName":"Xuyến","surName":"Ty Cáp","birthday":"1995-09-09","gender":"Nam","national":"Việt Nam","ethnic":"Kinh","religion":"Không có","bornAddress":"20 Giàng Thi, Dã Đinh, Vưu Điền","homeAddress":"71 Đống Xung, Thoa H’, Ung Hầu","citizenCardId":"1773548786","currentAddress":"123 Cát Danh, Ngụy Lỗ, Thôi Lâm","phoneNumber":"6529866559","email":"medelheit1t@linkedin.com","fatherPhoneNumber":"9543101708","motherPhoneNumber":"1306644331","isEnlisted":false,"draftDate":"","school":"UET","academyMethod":"Chính quy","levelOfAcademy":"Sinh viên","startedYear":"2007","schoolYearGroup":"K07","baseClass":"QH-2007","major":"Công nghệ kỹ thuật xây dựng"},
{"firstName":"Ðan","surName":"Thang Cống","birthday":"1995-08-29","gender":"Nam","national":"Việt Nam","ethnic":"Mông","religion":"Không có","bornAddress":"244 Khiếu Mục, Lều Thành, Chế Tạ","homeAddress":"258 Bành Thạch, Cao Lạc, Nhan Kông","citizenCardId":"2076839798","currentAddress":"493 Ân Đồng, Kông Hà, Liêu Bì","phoneNumber":"3178104071","email":"gmanneville1u@amazonaws.com","fatherPhoneNumber":"7213434357","motherPhoneNumber":"6029701608","isEnlisted":false,"draftDate":"","school":"UET","academyMethod":"Chính quy","levelOfAcademy":"Sinh viên","startedYear":"2018","schoolYearGroup":"K18","baseClass":"QH-2018","major":"Công nghệ thông tin"},
{"firstName":"Quế","surName":"Nhan Sùng","birthday":"1993-05-29","gender":"Nam","national":"Việt Nam","ethnic":"Kinh","religion":"Không có","bornAddress":"383 Lò Duy, Chế Trà, Ung Lư","homeAddress":"405 La Mã, Tào Quang, Hề Vạn","citizenCardId":"7306652060","currentAddress":"80 Thào Chương, Hồ Ong, Chúng Khoa","phoneNumber":"5731716026","email":"radlard1v@economist.com","fatherPhoneNumber":"4536581690","motherPhoneNumber":"2885715713","isEnlisted":false,"draftDate":"","school":"UET","academyMethod":"Chính quy","levelOfAcademy":"Sinh viên đã tốt nghiệp","startedYear":"2006","schoolYearGroup":"K06","baseClass":"QH-2006","major":"Công nghệ thông tin"},
{"firstName":"Tiêu","surName":"Bạc Cổ","birthday":"2005-03-17","gender":"Nam","national":"Việt Nam","ethnic":"Kinh","religion":"Không có","bornAddress":"46 Khương Phan, Bồ Bạch, Lương Đức","homeAddress":"113 Tán Đoàn, Lê Lyly, Chu/Châu Điền","citizenCardId":"1017797781","currentAddress":"482 Thi Tiếp, Ngọ Bồ, Quách Xa","phoneNumber":"4969069944","email":"kpouton1w@wikipedia.org","fatherPhoneNumber":"7821503081","motherPhoneNumber":"6924697447","isEnlisted":true,"draftDate":"2021-10-27","school":"UET","academyMethod":"Chính quy","levelOfAcademy":"Sinh viên","startedYear":"2012","schoolYearGroup":"K12","baseClass":"QH-2012","major":"Kỹ thuật Robot"},
{"firstName":"Sâm","surName":"Hà Bồ","birthday":"2000-05-13","gender":"Nữ","national":"Nga","ethnic":"Thái","religion":"Tin Lành","bornAddress":"152 Quang Yên, Duy Thất, Liên Trình","homeAddress":"294 Tiếp Hạ, Bá Hầu, Biện Phó","citizenCardId":"5031186771","currentAddress":"349 Trác Thân, Tinh Ung, Thào Ấu","phoneNumber":"6105859179","email":"gvelden1x@foxnews.com","fatherPhoneNumber":"7162029178","motherPhoneNumber":"6229983628","isEnlisted":false,"draftDate":"","school":"UET","academyMethod":"Chính quy","levelOfAcademy":"Sinh viên đã tốt nghiệp","startedYear":"2007","schoolYearGroup":"K07","baseClass":"CA-CLC-2007","major":"Công nghệ Hàng không vũ trụ"},
{"firstName":"Bảo","surName":"Quàng Tề","birthday":"1998-10-30","gender":"Nữ","national":"Việt Nam","ethnic":"Mông","religion":"Tin Lành","bornAddress":"323 Vũ Vưu, Tôn Lương, Ung Chiêm","homeAddress":"133 Thang Nông, Chương Đường, Hoàng Mang","citizenCardId":"0283951346","currentAddress":"116 Lã Thoa, Từ Đàm, Cam Mạc","phoneNumber":"8834908944","email":"swear1y@123-reg.co.uk","fatherPhoneNumber":"7655168365","motherPhoneNumber":"4005706828","isEnlisted":true,"draftDate":"2017-04-29","school":"UET","academyMethod":"Chính quy","levelOfAcademy":"Sinh viên","startedYear":"2019","schoolYearGroup":"K19","baseClass":"QH-2019","major":"Công nghệ kỹ thuật cơ điện tử"},
{"firstName":"Thuý","surName":"Sái Giàng","birthday":"1991-04-05","gender":"Nam","national":"Việt Nam","ethnic":"Kinh","religion":"Không có","bornAddress":"411 Triệu Kim, Mạch Đôn, Bàn Bình","homeAddress":"198 Trà Chương, Nhâm Cầm, Thang Tô","citizenCardId":"8040883156","currentAddress":"286 H’ma Linh, Lạc Văn, Yên Từ","phoneNumber":"4361259458","email":"gsoigoux1z@fastcompany.com","fatherPhoneNumber":"4818284865","motherPhoneNumber":"5691748789","isEnlisted":true,"draftDate":"2017-08-29","school":"UET","academyMethod":"Chính quy","levelOfAcademy":"Thạc sĩ","startedYear":"2007","schoolYearGroup":"K07","baseClass":"CA-CLC-2007","major":"Mạng máy tính và truyền thông dữ liệu"},
{"firstName":"Thao","surName":"Vạn Cát","birthday":"1997-09-01","gender":"Nam","national":"Việt Nam","ethnic":"Mông","religion":"Không có","bornAddress":"273 Liễu Ánh, Sầm Thào, Võ Đinh","homeAddress":"50 Mã Giang, Chương Mạc, Khu Đầu","citizenCardId":"7361855709","currentAddress":"235 Thịnh Kim, Cống Mã, Bàn Đan","phoneNumber":"7477818994","email":"bhaysom20@earthlink.net","fatherPhoneNumber":"7127190668","motherPhoneNumber":"4669799402","isEnlisted":false,"draftDate":"","school":"UET","academyMethod":"Chính quy","levelOfAcademy":"Thạc sĩ","startedYear":"2019","schoolYearGroup":"K19","baseClass":"QH-2019","major":"Công nghệ kỹ thuật xây dựng"},
{"firstName":"Vọng","surName":"Ngọ Đan","birthday":"2004-09-09","gender":"Nam","national":"Việt Nam","ethnic":"Tày","religion":"Hòa Hảo","bornAddress":"27 Duy Đống, Đường Chung, Mạch Liêu","homeAddress":"31 Cai Cảnh, Hướng Lục, Thành Bảo","citizenCardId":"9257286096","currentAddress":"321 Diêm Lăng, Phan Diệp, Mùa Xung","phoneNumber":"2277398462","email":"lgianullo21@scientificamerican.com","fatherPhoneNumber":"8779966308","motherPhoneNumber":"8078213165","isEnlisted":true,"draftDate":"2017-12-29","school":"UET","academyMethod":"Chính quy","levelOfAcademy":"Sinh viên đã tốt nghiệp","startedYear":"2007","schoolYearGroup":"K07","baseClass":"CA-CLC-2007","major":"Khoa Học Máy Tính"},
{"firstName":"Tuân","surName":"Sử Đăng","birthday":"2001-07-13","gender":"Nữ","national":"Việt Nam","ethnic":"Kinh","religion":"Không có","bornAddress":"358 H’ma Đường, Khoa Thân, Tông Thế","homeAddress":"369 Đái Hình, Lâm Lã, H’ Ung","citizenCardId":"9018199877","currentAddress":"38 Thang H’ma, Bạc Thào, Tòng Tề","phoneNumber":"4137363271","email":"dhutchinson22@mac.com","fatherPhoneNumber":"7567142169","motherPhoneNumber":"9615535913","isEnlisted":true,"draftDate":"2021-11-01","school":"UET","academyMethod":"Chính quy","levelOfAcademy":"Sinh viên đã tốt nghiệp","startedYear":"2016","schoolYearGroup":"K16","baseClass":"CA-CLC-2016","major":"Vật lý kỹ thuật"},
{"firstName":"Nhi","surName":"Từ Cự","birthday":"1994-08-03","gender":"Khác","national":"Việt Nam","ethnic":"Kinh","religion":"Không có","bornAddress":"137 Thào Tống, Sử Giáp, Khâu Ngân","homeAddress":"327 Chương Ông, Đống Liên, Bồ Thế","citizenCardId":"0875574866","currentAddress":"345 Điều Doãn, Quang Yên, Đèo Mùa","phoneNumber":"4191088218","email":"atibols23@unicef.org","fatherPhoneNumber":"4787413461","motherPhoneNumber":"6464346738","isEnlisted":true,"draftDate":"2021-03-23","school":"UET","academyMethod":"Chính quy","levelOfAcademy":"Sinh viên","startedYear":"2014","schoolYearGroup":"K14","baseClass":"CA-CLC-2014","major":"Điện Tử Viễn Thông"},
{"firstName":"Liên","surName":"Triệu Tông","birthday":"2000-09-07","gender":"Nữ","national":"Việt Nam","ethnic":"Kinh","religion":"Không có","bornAddress":"170 Tào Kiều, Giàng Giao, Đan Xung","homeAddress":"426 Ngọ Dư, Đầu Điền, Ty Đào","citizenCardId":"6978387452","currentAddress":"212 Tào Danh, Lạc Hình, Vạn Điêu","phoneNumber":"3226520571","email":"zgater24@imgur.com","fatherPhoneNumber":"5902643882","motherPhoneNumber":"9945139222","isEnlisted":false,"draftDate":"","school":"UET","academyMethod":"Chính quy","levelOfAcademy":"Sinh viên","startedYear":"2015","schoolYearGroup":"K15","baseClass":"QH-2015","major":"Công nghệ Hàng không vũ trụ"},
{"firstName":"Vĩnh","surName":"Ca Cam","birthday":"1992-12-02","gender":"Nam","national":"Việt Nam","ethnic":"Mông","religion":"Không có","bornAddress":"37 Lô Mầu/Màu, Đường Cáp, Chung Đan","homeAddress":"304 Lý H’, Tôn Mâu, Doãn Chử","citizenCardId":"2763287980","currentAddress":"105 Hán Lã, Lãnh Lý, Tiếp Khai","phoneNumber":"2584668081","email":"ethurman25@sogou.com","fatherPhoneNumber":"3889143315","motherPhoneNumber":"1385213038","isEnlisted":false,"draftDate":"","school":"UET","academyMethod":"Chính quy","levelOfAcademy":"Sinh viên đã tốt nghiệp","startedYear":"2008","schoolYearGroup":"K08","baseClass":"QH-2008","major":"Kỹ thuật máy tính"},
{"firstName":"Ngoạn","surName":"Đương Hàn","birthday":"1994-01-07","gender":"Nam","national":"Việt Nam","ethnic":"Tày","religion":"Không có","bornAddress":"286 Thoa Lại, Hồng Mang, Văn Cấn","homeAddress":"15 Khà Phú, Tiếp Lương, Điền Hán","citizenCardId":"0222779934","currentAddress":"13 Giáp Tuấn, Hồ Nhâm, Tinh Lâm","phoneNumber":"5511377545","email":"mhutchason26@seattletimes.com","fatherPhoneNumber":"2946739354","motherPhoneNumber":"6849637788","isEnlisted":false,"draftDate":"","school":"UET","academyMethod":"Chính quy","levelOfAcademy":"Sinh viên","startedYear":"2013","schoolYearGroup":"K13","baseClass":"CA-CLC-2013","major":"Kỹ thuật năng lượng"},
{"firstName":"Nghiệp","surName":"Dã Lê","birthday":"1994-02-01","gender":"Khác","national":"Việt Nam","ethnic":"Kinh","religion":"Không có","bornAddress":"357 Mâu Kông, Hứa Lê, Doãn Nghiêm","homeAddress":"346 Thôi Chung, H’nia Khu, Trần Trương","citizenCardId":"3859360124","currentAddress":"114 Lô Lê, Lỗ Cổ, Cao H’","phoneNumber":"1558897451","email":"bbarca27@spiegel.de","fatherPhoneNumber":"8439933803","motherPhoneNumber":"7738442031","isEnlisted":true,"draftDate":"2021-10-22","school":"UET","academyMethod":"Chính quy","levelOfAcademy":"Sinh viên","startedYear":"2009","schoolYearGroup":"K09","baseClass":"CA-CLC-2009","major":"Kỹ thuật điều khiển và tự động hóa"}]